atmos/__init__.py
atmos/constants.py
atmos/decorators.py
atmos/equations.py
atmos/solve.py
atmos/tests.py
atmos/util.py
atmos-0.2.6.dist-info/LICENSE.txt
atmos-0.2.6.dist-info/METADATA
atmos-0.2.6.dist-info/WHEEL
atmos-0.2.6.dist-info/top_level.txt
atmos-0.2.6.dist-info/RECORD
