Metadata-Version: 2.1
Name: atmos
Version: 0.2.6
Summary: Atmospheric sciences utility library
Home-page: https://github.com/mcgibbon/atmos
Author: Jeremy McGibbon
Author-email: mcgibbon@uw.edu
License: MIT
Keywords: atmos,atmospheric,equations,geoscience,science
Platform: UNKNOWN
License-File: LICENSE.txt
Requires-Dist: six (>=1.9.0)
Requires-Dist: numexpr (>=2.3.0)
Requires-Dist: numpy (>=1.6)
Requires-Dist: nose (>=1.3)
Requires-Dist: setuptools (>=15.0)
Requires-Dist: pint (>=0.6)
